pyanka/__init__.py
pyanka/anka.py
pyanka-0.0.2.dist-info/METADATA
pyanka-0.0.2.dist-info/WHEEL
pyanka-0.0.2.dist-info/top_level.txt
pyanka-0.0.2.dist-info/RECORD
