Metadata-Version: 2.1
Name: pyanka
Version: 0.0.2
Summary: An unofficial python wrapper library for Anka
Home-page: https://github.com/bitrise-io/PyAnka
Author: Sandor Feher
Author-email: sandor.feher@bitrise.io
License: UNKNOWN
Project-URL: Bug Tracker, https://github.com/bitrise-io/PyAnka/issues
Platform: UNKNOWN
Classifier: Programming Language :: Python :: 3
Classifier: Operating System :: OS Independent
Requires-Python: >=3
